llama_index/agent/azure_foundry_agent/__init__.py
llama_index/agent/azure_foundry_agent/base.py
llama_index_agent_azure_foundry-0.2.1.dist-info/METADATA
llama_index_agent_azure_foundry-0.2.1.dist-info/WHEEL
llama_index_agent_azure_foundry-0.2.1.dist-info/RECORD
