Metadata-Version: 2.4
Name: llama-index-agent-azure-foundry
Version: 0.2.1
Summary: llama-index agent azure integration
Author-email: Microsoft <SK-Support@microsoft.com>
License-Expression: MIT
Requires-Python: <4.0,>=3.9
Requires-Dist: azure-ai-agents>=1.0.0b3
Requires-Dist: azure-ai-projects>=1.0.0b11
Requires-Dist: azure-identity
Requires-Dist: llama-index-core<0.15,>=0.13.0
Requires-Dist: openai>=1.14.0
